image_processor-0.1.1.dist-info/METADATA
image_processor-0.1.1.dist-info/WHEEL
image_processor/__init__.py
image_processor/image_processor.cpython-38-x86_64-linux-gnu.so
image_processor-0.1.1.dist-info/RECORD
